{
  "test_training_user_001_21_cfr_part11_overview_basic_20cb84a6": {
    "assessment_attempts": [
      {
        "assessment_details": {
          "correct_answers": 5,
          "incorrect_answers": 0,
          "question_results": [
            {
              "correct_answer": "Electronic records and electronic signatures",
              "is_correct": true,
              "question_id": "q1",
              "user_answer": "Electronic records and electronic signatures"
            },
            {
              "correct_answer": "\u00a711.10(d)",
              "is_correct": true,
              "question_id": "q2",
              "user_answer": "\u00a711.10(d)"
            },
            {
              "correct_answer": "Name, date/time, and meaning of signature",
              "is_correct": true,
              "question_id": "q3",
              "user_answer": "Name, date/time, and meaning of signature"
            },
            {
              "correct_answer": false,
              "is_correct": true,
              "question_id": "q4",
              "user_answer": false
            },
            {
              "correct_answer": "Attributable, Legible, Contemporaneous, Original, Accurate + Complete, Consistent, Enduring, Available",
              "is_correct": true,
              "question_id": "q5",
              "user_answer": "Attributable, Legible, Contemporaneous, Original, Accurate + Complete, Consistent, Enduring, Available"
            }
          ],
          "total_questions": 5
        },
        "assessment_id": "part11_basic_001",
        "attempt_id": "287bc5d2-00c4-4911-9c5e-cfdddbaf87c2",
        "passed": true,
        "score": 100.0,
        "timestamp": "2025-08-13T15:35:53.053936+00:00"
      }
    ],
    "certification_issued": null,
    "completion_date": "2025-08-13T15:35:53.053936+00:00",
    "expiry_date": "2027-08-13T15:35:53.053936+00:00",
    "instructor_id": "training_admin_001",
    "is_current": true,
    "is_passing": true,
    "level": "basic",
    "module": "21_cfr_part11_overview",
    "record_id": "test_training_user_001_21_cfr_part11_overview_basic_20cb84a6",
    "score": 100.0,
    "start_date": "2025-08-13T15:35:53.050345+00:00",
    "status": "completed",
    "training_materials_accessed": [],
    "user_id": "test_training_user_001",
    "user_name": "Test User for Training"
  }
}